{
  "id": "40074376",
  "url": "https://issues.chromium.org/issues/40074376",
  "title": "Security: XSS in contenteditable elements via svg>use xlink:href ",
  "status": "Accepted",
  "severity": "S3-Low",
  "priority": "P3",
  "component": "Blink>DataTransfer, Blink>Editing>Paste, Blink>SecurityFeature>SanitizerAPI",
  "os_platforms": [
    "Android",
    "Fuchsia",
    "Linux",
    "Mac",
    "Windows",
    "ChromeOS"
  ],
  "chrome_version": null,
  "cve_ids": [],
  "reporter": "su...@gmail.com",
  "assignee": "da...@microsoft.com",
  "created_date": "2023-10-07T16:26:52+00:00",
  "modified_date": "2025-09-09T12:38:32+00:00",
  "public_issue": true,
  "bounty_confirmed": true,
  "bounty_amount": 500.0,
  "reward_amount_meta": 500.0,
  "inclusion_reason": "reward_amount_meta",
  "award_text_found": false,
  "award_text_source_update": null,
  "bounty_rationale": null,
  "attachments": [
    {
      "id": 53194060,
      "filename": "chrome_DCUwkDs5ih.png",
      "mime_type": "image/png",
      "size_bytes": 187428,
      "url": "https://issues.chromium.org/action/issues/40074376/attachments/53194060?download=true",
      "local_path": "attachments/chrome_DCUwkDs5ih.png"
    },
    {
      "id": 53194061,
      "filename": "firefox_jrT28YDg6P.png",
      "mime_type": "image/png",
      "size_bytes": 127778,
      "url": "https://issues.chromium.org/action/issues/40074376/attachments/53194061?download=true",
      "local_path": "attachments/firefox_jrT28YDg6P.png"
    },
    {
      "id": 53194062,
      "filename": "chrome_Z8E8AswCZw.mp4",
      "mime_type": "video/mp4",
      "size_bytes": 5075239,
      "url": "https://issues.chromium.org/action/issues/40074376/attachments/53194062?download=true",
      "local_path": "attachments/chrome_Z8E8AswCZw.mp4"
    },
    {
      "id": 53194098,
      "filename": "chrome_X4ixxcPPMo.png",
      "mime_type": "image/png",
      "size_bytes": 31319,
      "url": "https://issues.chromium.org/action/issues/40074376/attachments/53194098?download=true",
      "local_path": "attachments/chrome_X4ixxcPPMo.png"
    },
    {
      "id": 53194099,
      "filename": "firefox_Buvk3qW2QH.png",
      "mime_type": "image/png",
      "size_bytes": 53734,
      "url": "https://issues.chromium.org/action/issues/40074376/attachments/53194099?download=true",
      "local_path": "attachments/firefox_Buvk3qW2QH.png"
    },
    {
      "id": 53194169,
      "filename": "index.html",
      "mime_type": "text/plain",
      "size_bytes": 457,
      "url": "https://issues.chromium.org/action/issues/40074376/attachments/53194169?download=true",
      "local_path": "attachments/index.html"
    },
    {
      "id": 53194170,
      "filename": "chrome_WYTatcv8sG.png",
      "mime_type": "image/png",
      "size_bytes": 96225,
      "url": "https://issues.chromium.org/action/issues/40074376/attachments/53194170?download=true",
      "local_path": "attachments/chrome_WYTatcv8sG.png"
    },
    {
      "id": 62177457,
      "filename": "deleted",
      "mime_type": "application/octet-stream",
      "size_bytes": 0,
      "url": "https://issues.chromium.org/action/issues/40074376/attachments/62177457?download=true",
      "local_path": null
    }
  ],
  "update_count": 79,
  "description_snippet": "Heyy there,\r\n\r\nTaking an example from MDN for contenteditable elements:\r\n\r\n```html\r\n<blockquote contenteditable=\"true\">\r\n  <p>Edit this content to add your own quote</p>\r\n</blockquote>\r\n\r\n<cite contenteditable=\"true\">-- Write your own name here</cite>\r\n```\r\n\r\nElements with contenteditable attribute"
}