{
  "id": "40062206",
  "url": "https://issues.chromium.org/issues/40062206",
  "title": "Security: heap-use-after-free in blink::PropertyTreeManager::EnsureCompositorTransformNode",
  "status": "Fixed",
  "severity": "S3-Low",
  "priority": "P1",
  "component": "Internals>Compositing",
  "os_platforms": [
    "Android",
    "Fuchsia",
    "Linux",
    "Mac",
    "Windows",
    "ChromeOS"
  ],
  "chrome_version": null,
  "cve_ids": [],
  "reporter": "st...@gmail.com",
  "assignee": "xi...@chromium.org",
  "created_date": "2022-12-13T01:09:46+00:00",
  "modified_date": "2023-04-18T17:33:39+00:00",
  "public_issue": true,
  "bounty_confirmed": true,
  "bounty_amount": 8000.0,
  "reward_amount_meta": 8000.0,
  "inclusion_reason": "reward_amount_meta",
  "award_text_found": false,
  "award_text_source_update": null,
  "bounty_rationale": null,
  "attachments": [
    {
      "id": 53283089,
      "filename": "poc.html",
      "mime_type": "text/plain",
      "size_bytes": 643,
      "url": "https://issues.chromium.org/action/issues/40062206/attachments/53283089?download=true",
      "local_path": "attachments/poc.html"
    },
    {
      "id": 53283090,
      "filename": "portal.html",
      "mime_type": "text/plain",
      "size_bytes": 147,
      "url": "https://issues.chromium.org/action/issues/40062206/attachments/53283090?download=true",
      "local_path": "attachments/portal.html"
    },
    {
      "id": 53283091,
      "filename": "poc.webm",
      "mime_type": "video/webm",
      "size_bytes": 1379348,
      "url": "https://issues.chromium.org/action/issues/40062206/attachments/53283091?download=true",
      "local_path": "attachments/poc.webm"
    },
    {
      "id": 53283109,
      "filename": "new-poc.html",
      "mime_type": "text/plain",
      "size_bytes": 763,
      "url": "https://issues.chromium.org/action/issues/40062206/attachments/53283109?download=true",
      "local_path": "attachments/new-poc.html"
    },
    {
      "id": 53283110,
      "filename": "new-poc.webm",
      "mime_type": "video/webm",
      "size_bytes": 717587,
      "url": "https://issues.chromium.org/action/issues/40062206/attachments/53283110?download=true",
      "local_path": "attachments/new-poc.webm"
    },
    {
      "id": 53283120,
      "filename": "asan.log",
      "mime_type": "text/plain",
      "size_bytes": 26792,
      "url": "https://issues.chromium.org/action/issues/40062206/attachments/53283120?download=true",
      "local_path": "attachments/asan.log"
    }
  ],
  "update_count": 29,
  "description_snippet": "**VULNERABILITY DETAILS**   \nA portal adopting a portal predecessor selected in a nested <selectmenu> causes UaF.  \n  \n**VERSION**   \nChrome Version: 110.0.5475.0  \nOperating System: Windows  \n  \n**REPRODUCTION CASE**   \n1. python3 -m http.server 9000  \n2. chrome --enable-features=Portals --enable-e"
}