{
  "id": "40058369",
  "url": "https://issues.chromium.org/issues/40058369",
  "title": "UAF in PrintViewManagerBase",
  "status": "Assigned",
  "severity": "S3-Low",
  "priority": "P1",
  "component": "Internals>Printing",
  "os_platforms": [
    "Linux",
    "Mac",
    "Windows",
    "ChromeOS"
  ],
  "chrome_version": null,
  "cve_ids": [],
  "reporter": "ro...@gmail.com",
  "assignee": "aw...@chromium.org",
  "created_date": null,
  "modified_date": null,
  "public_issue": true,
  "bounty_confirmed": true,
  "bounty_amount": 15000.0,
  "reward_amount_meta": 15000.0,
  "inclusion_reason": "reward_amount_meta",
  "award_text_found": false,
  "award_text_source_update": null,
  "bounty_rationale": null,
  "attachments": [],
  "update_count": 0,
  "description_snippet": ""
}